{
  "id": "01KNR335K9WHC903B4QT15MW4B",
  "traceId": "b2ea38771710f1e92e26a3e6ac3a95fc",
  "serviceName": "order-service",
  "startedAt": 1775703791209,
  "endedAt": 1775703791217,
  "events": [
    {
      "id": "01KNR335K946QNQAKP31WQR69B",
      "traceId": "b2ea38771710f1e92e26a3e6ac3a95fc",
      "spanId": "9923c77572c21ea4",
      "parentSpanId": null,
      "hlc": {
        "wallTime": 1775703791209,
        "logical": 0,
        "nodeId": "order-service-01KNR335"
      },
      "wallClock": 1775703791209,
      "type": "http_request_in",
      "serviceName": "order-service",
      "operationName": "POST /api/orders",
      "sequence": 0,
      "data": {
        "method": "POST",
        "url": "/api/orders",
        "path": "/api/orders",
        "query": {},
        "headers": {
          "host": "localhost:3001",
          "connection": "keep-alive",
          "content-type": "application/json",
          "accept": "*/*",
          "accept-language": "*",
          "sec-fetch-mode": "cors",
          "user-agent": "node",
          "accept-encoding": "gzip, deflate",
          "content-length": "39"
        },
        "body": {
          "userId": "4",
          "item": "PARADOX License"
        },
        "ip": "::1"
      },
      "durationMs": 0,
      "error": null,
      "tags": {}
    },
    {
      "id": "01KNR335K9SMN19E964D2FAK36",
      "traceId": "b2ea38771710f1e92e26a3e6ac3a95fc",
      "spanId": "9923c77572c21ea4",
      "parentSpanId": null,
      "hlc": {
        "wallTime": 1775703791209,
        "logical": 1,
        "nodeId": "order-service-01KNR335"
      },
      "wallClock": 1775703791209,
      "type": "timestamp",
      "serviceName": "order-service",
      "operationName": "Date.now()",
      "sequence": 1,
      "data": {
        "value": 1775703791209
      },
      "durationMs": 0,
      "error": null,
      "tags": {}
    },
    {
      "id": "01KNR335K940SM6MR7E2XT1MZH",
      "traceId": "b2ea38771710f1e92e26a3e6ac3a95fc",
      "spanId": "9923c77572c21ea4",
      "parentSpanId": null,
      "hlc": {
        "wallTime": 1775703791209,
        "logical": 2,
        "nodeId": "order-service-01KNR335"
      },
      "wallClock": 1775703791209,
      "type": "random",
      "serviceName": "order-service",
      "operationName": "Math.random()",
      "sequence": 2,
      "data": {
        "value": 0.7212378492073839
      },
      "durationMs": 0,
      "error": null,
      "tags": {}
    },
    {
      "id": "01KNR335KA1S52XY3WT9ZRBPAN",
      "traceId": "b2ea38771710f1e92e26a3e6ac3a95fc",
      "spanId": "9923c77572c21ea4",
      "parentSpanId": null,
      "hlc": {
        "wallTime": 1775703791210,
        "logical": 1,
        "nodeId": "order-service-01KNR335"
      },
      "wallClock": 1775703791210,
      "type": "timestamp",
      "serviceName": "order-service",
      "operationName": "Date.now()",
      "sequence": 3,
      "data": {
        "value": 1775703791210
      },
      "durationMs": 0,
      "error": null,
      "tags": {}
    },
    {
      "id": "01KNR335KAPBVHS6T5A6DSACVE",
      "traceId": "b2ea38771710f1e92e26a3e6ac3a95fc",
      "spanId": "9923c77572c21ea4",
      "parentSpanId": null,
      "hlc": {
        "wallTime": 1775703791210,
        "logical": 2,
        "nodeId": "order-service-01KNR335"
      },
      "wallClock": 1775703791210,
      "type": "random",
      "serviceName": "order-service",
      "operationName": "Math.random()",
      "sequence": 4,
      "data": {
        "value": 0.7029444350981414
      },
      "durationMs": 0,
      "error": null,
      "tags": {}
    },
    {
      "id": "01KNR335KAP51KNEH12TG0ZWKZ",
      "traceId": "b2ea38771710f1e92e26a3e6ac3a95fc",
      "spanId": "9923c77572c21ea4",
      "parentSpanId": null,
      "hlc": {
        "wallTime": 1775703791210,
        "logical": 3,
        "nodeId": "order-service-01KNR335"
      },
      "wallClock": 1775703791210,
      "type": "random",
      "serviceName": "order-service",
      "operationName": "Math.random()",
      "sequence": 5,
      "data": {
        "value": 0.7207411627814007
      },
      "durationMs": 0,
      "error": null,
      "tags": {}
    },
    {
      "id": "01KNR335KAK51124BTH23BYDMV",
      "traceId": "b2ea38771710f1e92e26a3e6ac3a95fc",
      "spanId": "9923c77572c21ea4",
      "parentSpanId": null,
      "hlc": {
        "wallTime": 1775703791210,
        "logical": 4,
        "nodeId": "order-service-01KNR335"
      },
      "wallClock": 1775703791210,
      "type": "random",
      "serviceName": "order-service",
      "operationName": "Math.random()",
      "sequence": 6,
      "data": {
        "value": 0.7113452940759623
      },
      "durationMs": 0,
      "error": null,
      "tags": {}
    },
    {
      "id": "01KNR335KAGQ3FYEDTXG337WKA",
      "traceId": "b2ea38771710f1e92e26a3e6ac3a95fc",
      "spanId": "9923c77572c21ea4",
      "parentSpanId": null,
      "hlc": {
        "wallTime": 1775703791210,
        "logical": 5,
        "nodeId": "order-service-01KNR335"
      },
      "wallClock": 1775703791210,
      "type": "random",
      "serviceName": "order-service",
      "operationName": "Math.random()",
      "sequence": 7,
      "data": {
        "value": 0.8719799106284328
      },
      "durationMs": 0,
      "error": null,
      "tags": {}
    },
    {
      "id": "01KNR335KAJ95VC5BPS5B6FBMM",
      "traceId": "b2ea38771710f1e92e26a3e6ac3a95fc",
      "spanId": "9923c77572c21ea4",
      "parentSpanId": null,
      "hlc": {
        "wallTime": 1775703791210,
        "logical": 6,
        "nodeId": "order-service-01KNR335"
      },
      "wallClock": 1775703791210,
      "type": "random",
      "serviceName": "order-service",
      "operationName": "Math.random()",
      "sequence": 8,
      "data": {
        "value": 0.6508394980054312
      },
      "durationMs": 0,
      "error": null,
      "tags": {}
    },
    {
      "id": "01KNR335KAMD2Y4QQ2Z1D03PTK",
      "traceId": "b2ea38771710f1e92e26a3e6ac3a95fc",
      "spanId": "9923c77572c21ea4",
      "parentSpanId": null,
      "hlc": {
        "wallTime": 1775703791210,
        "logical": 7,
        "nodeId": "order-service-01KNR335"
      },
      "wallClock": 1775703791210,
      "type": "random",
      "serviceName": "order-service",
      "operationName": "Math.random()",
      "sequence": 9,
      "data": {
        "value": 0.34385864435801383
      },
      "durationMs": 0,
      "error": null,
      "tags": {}
    },
    {
      "id": "01KNR335KAGFWWNKVRMXKMATYC",
      "traceId": "b2ea38771710f1e92e26a3e6ac3a95fc",
      "spanId": "9923c77572c21ea4",
      "parentSpanId": null,
      "hlc": {
        "wallTime": 1775703791210,
        "logical": 8,
        "nodeId": "order-service-01KNR335"
      },
      "wallClock": 1775703791210,
      "type": "random",
      "serviceName": "order-service",
      "operationName": "Math.random()",
      "sequence": 10,
      "data": {
        "value": 0.02373234000581259
      },
      "durationMs": 0,
      "error": null,
      "tags": {}
    },
    {
      "id": "01KNR335KAF472WQBY7C358PS2",
      "traceId": "b2ea38771710f1e92e26a3e6ac3a95fc",
      "spanId": "9923c77572c21ea4",
      "parentSpanId": null,
      "hlc": {
        "wallTime": 1775703791210,
        "logical": 9,
        "nodeId": "order-service-01KNR335"
      },
      "wallClock": 1775703791210,
      "type": "random",
      "serviceName": "order-service",
      "operationName": "Math.random()",
      "sequence": 11,
      "data": {
        "value": 0.08420294635068981
      },
      "durationMs": 0,
      "error": null,
      "tags": {}
    },
    {
      "id": "01KNR335KAN7NH2Q03QWYNQW0P",
      "traceId": "b2ea38771710f1e92e26a3e6ac3a95fc",
      "spanId": "9923c77572c21ea4",
      "parentSpanId": null,
      "hlc": {
        "wallTime": 1775703791210,
        "logical": 10,
        "nodeId": "order-service-01KNR335"
      },
      "wallClock": 1775703791210,
      "type": "random",
      "serviceName": "order-service",
      "operationName": "Math.random()",
      "sequence": 12,
      "data": {
        "value": 0.7785471792348024
      },
      "durationMs": 0,
      "error": null,
      "tags": {}
    },
    {
      "id": "01KNR335KAQDVK2F0E0ZCX3WFP",
      "traceId": "b2ea38771710f1e92e26a3e6ac3a95fc",
      "spanId": "9923c77572c21ea4",
      "parentSpanId": null,
      "hlc": {
        "wallTime": 1775703791210,
        "logical": 11,
        "nodeId": "order-service-01KNR335"
      },
      "wallClock": 1775703791210,
      "type": "random",
      "serviceName": "order-service",
      "operationName": "Math.random()",
      "sequence": 13,
      "data": {
        "value": 0.6816002262689626
      },
      "durationMs": 0,
      "error": null,
      "tags": {}
    },
    {
      "id": "01KNR335KAXW1C9JAXSHHDX7NF",
      "traceId": "b2ea38771710f1e92e26a3e6ac3a95fc",
      "spanId": "9923c77572c21ea4",
      "parentSpanId": null,
      "hlc": {
        "wallTime": 1775703791210,
        "logical": 12,
        "nodeId": "order-service-01KNR335"
      },
      "wallClock": 1775703791210,
      "type": "random",
      "serviceName": "order-service",
      "operationName": "Math.random()",
      "sequence": 14,
      "data": {
        "value": 0.6596696840559133
      },
      "durationMs": 0,
      "error": null,
      "tags": {}
    },
    {
      "id": "01KNR335KAWG71R1S1640J0Y5M",
      "traceId": "b2ea38771710f1e92e26a3e6ac3a95fc",
      "spanId": "9923c77572c21ea4",
      "parentSpanId": null,
      "hlc": {
        "wallTime": 1775703791210,
        "logical": 13,
        "nodeId": "order-service-01KNR335"
      },
      "wallClock": 1775703791210,
      "type": "random",
      "serviceName": "order-service",
      "operationName": "Math.random()",
      "sequence": 15,
      "data": {
        "value": 0.40876993261132866
      },
      "durationMs": 0,
      "error": null,
      "tags": {}
    },
    {
      "id": "01KNR335KAZRDVVP9RJM4A31YP",
      "traceId": "b2ea38771710f1e92e26a3e6ac3a95fc",
      "spanId": "9923c77572c21ea4",
      "parentSpanId": null,
      "hlc": {
        "wallTime": 1775703791210,
        "logical": 14,
        "nodeId": "order-service-01KNR335"
      },
      "wallClock": 1775703791210,
      "type": "random",
      "serviceName": "order-service",
      "operationName": "Math.random()",
      "sequence": 16,
      "data": {
        "value": 0.5813696497550972
      },
      "durationMs": 0,
      "error": null,
      "tags": {}
    },
    {
      "id": "01KNR335KABZ8F08ZZHPH86CZ2",
      "traceId": "b2ea38771710f1e92e26a3e6ac3a95fc",
      "spanId": "9923c77572c21ea4",
      "parentSpanId": null,
      "hlc": {
        "wallTime": 1775703791210,
        "logical": 15,
        "nodeId": "order-service-01KNR335"
      },
      "wallClock": 1775703791210,
      "type": "random",
      "serviceName": "order-service",
      "operationName": "Math.random()",
      "sequence": 17,
      "data": {
        "value": 0.39632059961303445
      },
      "durationMs": 0,
      "error": null,
      "tags": {}
    },
    {
      "id": "01KNR335KA3X7KS4J7X3R03MTM",
      "traceId": "b2ea38771710f1e92e26a3e6ac3a95fc",
      "spanId": "9923c77572c21ea4",
      "parentSpanId": null,
      "hlc": {
        "wallTime": 1775703791210,
        "logical": 16,
        "nodeId": "order-service-01KNR335"
      },
      "wallClock": 1775703791210,
      "type": "random",
      "serviceName": "order-service",
      "operationName": "Math.random()",
      "sequence": 18,
      "data": {
        "value": 0.8024040639071727
      },
      "durationMs": 0,
      "error": null,
      "tags": {}
    },
    {
      "id": "01KNR335KANJCMHZ1GZGTBVCGG",
      "traceId": "b2ea38771710f1e92e26a3e6ac3a95fc",
      "spanId": "9923c77572c21ea4",
      "parentSpanId": null,
      "hlc": {
        "wallTime": 1775703791210,
        "logical": 17,
        "nodeId": "order-service-01KNR335"
      },
      "wallClock": 1775703791210,
      "type": "random",
      "serviceName": "order-service",
      "operationName": "Math.random()",
      "sequence": 19,
      "data": {
        "value": 0.6353548568037116
      },
      "durationMs": 0,
      "error": null,
      "tags": {}
    },
    {
      "id": "01KNR335KAPQPVMB02RNNDJCSM",
      "traceId": "b2ea38771710f1e92e26a3e6ac3a95fc",
      "spanId": "9923c77572c21ea4",
      "parentSpanId": null,
      "hlc": {
        "wallTime": 1775703791210,
        "logical": 0,
        "nodeId": "order-service-01KNR335"
      },
      "wallClock": 1775703791210,
      "type": "http_request_out",
      "serviceName": "order-service",
      "operationName": "GET http://localhost:3002/api/users/4",
      "sequence": 20,
      "data": {
        "url": "http://localhost:3002/api/users/4",
        "method": "GET",
        "headers": {
          "traceparent": "00-b2ea38771710f1e92e26a3e6ac3a95fc-9923c77572c21ea4-01",
          "x-paradox-hlc": "{\"wallTime\":1775703791209,\"logical\":2,\"nodeId\":\"order-service-01KNR335\"}"
        },
        "body": null
      },
      "durationMs": 0,
      "error": null,
      "tags": {}
    },
    {
      "id": "01KNR335KGDFM4CWFHN4ANQVF0",
      "traceId": "b2ea38771710f1e92e26a3e6ac3a95fc",
      "spanId": "9923c77572c21ea4",
      "parentSpanId": null,
      "hlc": {
        "wallTime": 1775703791216,
        "logical": 1,
        "nodeId": "order-service-01KNR335"
      },
      "wallClock": 1775703791216,
      "type": "timestamp",
      "serviceName": "order-service",
      "operationName": "Date.now()",
      "sequence": 21,
      "data": {
        "value": 1775703791216
      },
      "durationMs": 0,
      "error": null,
      "tags": {}
    },
    {
      "id": "01KNR335KGSZ8SXV5H8Q7D9XTB",
      "traceId": "b2ea38771710f1e92e26a3e6ac3a95fc",
      "spanId": "9923c77572c21ea4",
      "parentSpanId": null,
      "hlc": {
        "wallTime": 1775703791216,
        "logical": 2,
        "nodeId": "order-service-01KNR335"
      },
      "wallClock": 1775703791216,
      "type": "random",
      "serviceName": "order-service",
      "operationName": "Math.random()",
      "sequence": 22,
      "data": {
        "value": 0.5428563311114285
      },
      "durationMs": 0,
      "error": null,
      "tags": {}
    },
    {
      "id": "01KNR335KGW2EZ6J0CH0VVSCXG",
      "traceId": "b2ea38771710f1e92e26a3e6ac3a95fc",
      "spanId": "9923c77572c21ea4",
      "parentSpanId": null,
      "hlc": {
        "wallTime": 1775703791216,
        "logical": 3,
        "nodeId": "order-service-01KNR335"
      },
      "wallClock": 1775703791216,
      "type": "random",
      "serviceName": "order-service",
      "operationName": "Math.random()",
      "sequence": 23,
      "data": {
        "value": 0.9101180312809053
      },
      "durationMs": 0,
      "error": null,
      "tags": {}
    },
    {
      "id": "01KNR335KGNCZBE6FHWDEDX8DY",
      "traceId": "b2ea38771710f1e92e26a3e6ac3a95fc",
      "spanId": "9923c77572c21ea4",
      "parentSpanId": null,
      "hlc": {
        "wallTime": 1775703791216,
        "logical": 4,
        "nodeId": "order-service-01KNR335"
      },
      "wallClock": 1775703791216,
      "type": "random",
      "serviceName": "order-service",
      "operationName": "Math.random()",
      "sequence": 24,
      "data": {
        "value": 0.7247593215836773
      },
      "durationMs": 0,
      "error": null,
      "tags": {}
    },
    {
      "id": "01KNR335KG2T3KBDJ78JC3JQTJ",
      "traceId": "b2ea38771710f1e92e26a3e6ac3a95fc",
      "spanId": "9923c77572c21ea4",
      "parentSpanId": null,
      "hlc": {
        "wallTime": 1775703791216,
        "logical": 5,
        "nodeId": "order-service-01KNR335"
      },
      "wallClock": 1775703791216,
      "type": "random",
      "serviceName": "order-service",
      "operationName": "Math.random()",
      "sequence": 25,
      "data": {
        "value": 0.06761306908438502
      },
      "durationMs": 0,
      "error": null,
      "tags": {}
    },
    {
      "id": "01KNR335KG17PNWA37WQ68EF0A",
      "traceId": "b2ea38771710f1e92e26a3e6ac3a95fc",
      "spanId": "9923c77572c21ea4",
      "parentSpanId": null,
      "hlc": {
        "wallTime": 1775703791216,
        "logical": 6,
        "nodeId": "order-service-01KNR335"
      },
      "wallClock": 1775703791216,
      "type": "random",
      "serviceName": "order-service",
      "operationName": "Math.random()",
      "sequence": 26,
      "data": {
        "value": 0.13111274005659734
      },
      "durationMs": 0,
      "error": null,
      "tags": {}
    },
    {
      "id": "01KNR335KG07R0H60Y14M7SY7Q",
      "traceId": "b2ea38771710f1e92e26a3e6ac3a95fc",
      "spanId": "9923c77572c21ea4",
      "parentSpanId": null,
      "hlc": {
        "wallTime": 1775703791216,
        "logical": 7,
        "nodeId": "order-service-01KNR335"
      },
      "wallClock": 1775703791216,
      "type": "random",
      "serviceName": "order-service",
      "operationName": "Math.random()",
      "sequence": 27,
      "data": {
        "value": 0.4484867010187735
      },
      "durationMs": 0,
      "error": null,
      "tags": {}
    },
    {
      "id": "01KNR335KG8YMR589K1G8VBM0C",
      "traceId": "b2ea38771710f1e92e26a3e6ac3a95fc",
      "spanId": "9923c77572c21ea4",
      "parentSpanId": null,
      "hlc": {
        "wallTime": 1775703791216,
        "logical": 8,
        "nodeId": "order-service-01KNR335"
      },
      "wallClock": 1775703791216,
      "type": "random",
      "serviceName": "order-service",
      "operationName": "Math.random()",
      "sequence": 28,
      "data": {
        "value": 0.30023572251501807
      },
      "durationMs": 0,
      "error": null,
      "tags": {}
    },
    {
      "id": "01KNR335KGVM1C09GB5TZXBPBH",
      "traceId": "b2ea38771710f1e92e26a3e6ac3a95fc",
      "spanId": "9923c77572c21ea4",
      "parentSpanId": null,
      "hlc": {
        "wallTime": 1775703791216,
        "logical": 9,
        "nodeId": "order-service-01KNR335"
      },
      "wallClock": 1775703791216,
      "type": "random",
      "serviceName": "order-service",
      "operationName": "Math.random()",
      "sequence": 29,
      "data": {
        "value": 0.29479827362822786
      },
      "durationMs": 0,
      "error": null,
      "tags": {}
    },
    {
      "id": "01KNR335KG0S6GN6S85RFTVVJD",
      "traceId": "b2ea38771710f1e92e26a3e6ac3a95fc",
      "spanId": "9923c77572c21ea4",
      "parentSpanId": null,
      "hlc": {
        "wallTime": 1775703791216,
        "logical": 10,
        "nodeId": "order-service-01KNR335"
      },
      "wallClock": 1775703791216,
      "type": "random",
      "serviceName": "order-service",
      "operationName": "Math.random()",
      "sequence": 30,
      "data": {
        "value": 0.7243030591423163
      },
      "durationMs": 0,
      "error": null,
      "tags": {}
    },
    {
      "id": "01KNR335KGW65E63PY05KC35G0",
      "traceId": "b2ea38771710f1e92e26a3e6ac3a95fc",
      "spanId": "9923c77572c21ea4",
      "parentSpanId": null,
      "hlc": {
        "wallTime": 1775703791216,
        "logical": 11,
        "nodeId": "order-service-01KNR335"
      },
      "wallClock": 1775703791216,
      "type": "random",
      "serviceName": "order-service",
      "operationName": "Math.random()",
      "sequence": 31,
      "data": {
        "value": 0.24574527486738973
      },
      "durationMs": 0,
      "error": null,
      "tags": {}
    },
    {
      "id": "01KNR335KGZ3MTZKHNP4NVDQ93",
      "traceId": "b2ea38771710f1e92e26a3e6ac3a95fc",
      "spanId": "9923c77572c21ea4",
      "parentSpanId": null,
      "hlc": {
        "wallTime": 1775703791216,
        "logical": 12,
        "nodeId": "order-service-01KNR335"
      },
      "wallClock": 1775703791216,
      "type": "random",
      "serviceName": "order-service",
      "operationName": "Math.random()",
      "sequence": 32,
      "data": {
        "value": 0.6207137231544821
      },
      "durationMs": 0,
      "error": null,
      "tags": {}
    },
    {
      "id": "01KNR335KGXXW4PC94R7T2ZVB6",
      "traceId": "b2ea38771710f1e92e26a3e6ac3a95fc",
      "spanId": "9923c77572c21ea4",
      "parentSpanId": null,
      "hlc": {
        "wallTime": 1775703791216,
        "logical": 13,
        "nodeId": "order-service-01KNR335"
      },
      "wallClock": 1775703791216,
      "type": "random",
      "serviceName": "order-service",
      "operationName": "Math.random()",
      "sequence": 33,
      "data": {
        "value": 0.5855799648443999
      },
      "durationMs": 0,
      "error": null,
      "tags": {}
    },
    {
      "id": "01KNR335KGYNWE8JMHA6RZ95DH",
      "traceId": "b2ea38771710f1e92e26a3e6ac3a95fc",
      "spanId": "9923c77572c21ea4",
      "parentSpanId": null,
      "hlc": {
        "wallTime": 1775703791216,
        "logical": 14,
        "nodeId": "order-service-01KNR335"
      },
      "wallClock": 1775703791216,
      "type": "random",
      "serviceName": "order-service",
      "operationName": "Math.random()",
      "sequence": 34,
      "data": {
        "value": 0.9578847408158068
      },
      "durationMs": 0,
      "error": null,
      "tags": {}
    },
    {
      "id": "01KNR335KGMMC92B8MFBHW6292",
      "traceId": "b2ea38771710f1e92e26a3e6ac3a95fc",
      "spanId": "9923c77572c21ea4",
      "parentSpanId": null,
      "hlc": {
        "wallTime": 1775703791216,
        "logical": 15,
        "nodeId": "order-service-01KNR335"
      },
      "wallClock": 1775703791216,
      "type": "random",
      "serviceName": "order-service",
      "operationName": "Math.random()",
      "sequence": 35,
      "data": {
        "value": 0.9197264972502005
      },
      "durationMs": 0,
      "error": null,
      "tags": {}
    },
    {
      "id": "01KNR335KGFQ97WGVYVQJJG91K",
      "traceId": "b2ea38771710f1e92e26a3e6ac3a95fc",
      "spanId": "9923c77572c21ea4",
      "parentSpanId": null,
      "hlc": {
        "wallTime": 1775703791216,
        "logical": 16,
        "nodeId": "order-service-01KNR335"
      },
      "wallClock": 1775703791216,
      "type": "random",
      "serviceName": "order-service",
      "operationName": "Math.random()",
      "sequence": 36,
      "data": {
        "value": 0.7884171712916562
      },
      "durationMs": 0,
      "error": null,
      "tags": {}
    },
    {
      "id": "01KNR335KGHE7N1JTVP66SD60Z",
      "traceId": "b2ea38771710f1e92e26a3e6ac3a95fc",
      "spanId": "9923c77572c21ea4",
      "parentSpanId": null,
      "hlc": {
        "wallTime": 1775703791216,
        "logical": 17,
        "nodeId": "order-service-01KNR335"
      },
      "wallClock": 1775703791216,
      "type": "random",
      "serviceName": "order-service",
      "operationName": "Math.random()",
      "sequence": 37,
      "data": {
        "value": 0.7082938108668244
      },
      "durationMs": 0,
      "error": null,
      "tags": {}
    },
    {
      "id": "01KNR335KGHXQ24E99Q7KJYXSP",
      "traceId": "b2ea38771710f1e92e26a3e6ac3a95fc",
      "spanId": "9923c77572c21ea4",
      "parentSpanId": null,
      "hlc": {
        "wallTime": 1775703791216,
        "logical": 0,
        "nodeId": "order-service-01KNR335"
      },
      "wallClock": 1775703791216,
      "type": "http_response_in",
      "serviceName": "order-service",
      "operationName": "200 GET http://localhost:3002/api/users/4",
      "sequence": 38,
      "data": {
        "status": 200,
        "statusText": "OK",
        "headers": {
          "connection": "keep-alive",
          "content-length": "156",
          "content-type": "application/json; charset=utf-8",
          "date": "Thu, 09 Apr 2026 03:03:11 GMT",
          "etag": "W/\"9c-OZeVGX2/NJ5TyKXiHLeLwTUwiKI\"",
          "keep-alive": "timeout=5",
          "traceparent": "00-b2ea38771710f1e92e26a3e6ac3a95fc-dc95021eb60cda5c-01",
          "x-powered-by": "Express"
        },
        "body": {
          "user": {
            "id": "4",
            "name": "Fatma Celik",
            "email": "fatma@paradox.dev",
            "credit": 50,
            "role": "user"
          },
          "meta": {
            "lookupTime": 1775703791213,
            "requestToken": "tl72hqtk"
          }
        }
      },
      "durationMs": 6,
      "error": null,
      "tags": {}
    },
    {
      "id": "01KNR335KGCCR5PVMW3SHNNW44",
      "traceId": "b2ea38771710f1e92e26a3e6ac3a95fc",
      "spanId": "9923c77572c21ea4",
      "parentSpanId": null,
      "hlc": {
        "wallTime": 1775703791216,
        "logical": 18,
        "nodeId": "order-service-01KNR335"
      },
      "wallClock": 1775703791216,
      "type": "random",
      "serviceName": "order-service",
      "operationName": "Math.random()",
      "sequence": 39,
      "data": {
        "value": 0.50079804534712
      },
      "durationMs": 0,
      "error": null,
      "tags": {}
    },
    {
      "id": "01KNR335KHC5HP2X2CXE96820V",
      "traceId": "b2ea38771710f1e92e26a3e6ac3a95fc",
      "spanId": "9923c77572c21ea4",
      "parentSpanId": null,
      "hlc": {
        "wallTime": 1775703791217,
        "logical": 1,
        "nodeId": "order-service-01KNR335"
      },
      "wallClock": 1775703791217,
      "type": "timestamp",
      "serviceName": "order-service",
      "operationName": "Date.now()",
      "sequence": 40,
      "data": {
        "value": 1775703791217
      },
      "durationMs": 0,
      "error": null,
      "tags": {}
    },
    {
      "id": "01KNR335KH714KZKFXPWXEZ4X1",
      "traceId": "b2ea38771710f1e92e26a3e6ac3a95fc",
      "spanId": "9923c77572c21ea4",
      "parentSpanId": null,
      "hlc": {
        "wallTime": 1775703791217,
        "logical": 2,
        "nodeId": "order-service-01KNR335"
      },
      "wallClock": 1775703791217,
      "type": "random",
      "serviceName": "order-service",
      "operationName": "Math.random()",
      "sequence": 41,
      "data": {
        "value": 0.5408879919855103
      },
      "durationMs": 0,
      "error": null,
      "tags": {}
    },
    {
      "id": "01KNR335KHNH9BNHJEYGCJDS2K",
      "traceId": "b2ea38771710f1e92e26a3e6ac3a95fc",
      "spanId": "9923c77572c21ea4",
      "parentSpanId": null,
      "hlc": {
        "wallTime": 1775703791217,
        "logical": 3,
        "nodeId": "order-service-01KNR335"
      },
      "wallClock": 1775703791217,
      "type": "random",
      "serviceName": "order-service",
      "operationName": "Math.random()",
      "sequence": 42,
      "data": {
        "value": 0.15166160640043014
      },
      "durationMs": 0,
      "error": null,
      "tags": {}
    },
    {
      "id": "01KNR335KHAAXTX4F5M5PAY84Q",
      "traceId": "b2ea38771710f1e92e26a3e6ac3a95fc",
      "spanId": "9923c77572c21ea4",
      "parentSpanId": null,
      "hlc": {
        "wallTime": 1775703791217,
        "logical": 4,
        "nodeId": "order-service-01KNR335"
      },
      "wallClock": 1775703791217,
      "type": "random",
      "serviceName": "order-service",
      "operationName": "Math.random()",
      "sequence": 43,
      "data": {
        "value": 0.4354963154134288
      },
      "durationMs": 0,
      "error": null,
      "tags": {}
    },
    {
      "id": "01KNR335KHZTBC5WBGB1D2E98B",
      "traceId": "b2ea38771710f1e92e26a3e6ac3a95fc",
      "spanId": "9923c77572c21ea4",
      "parentSpanId": null,
      "hlc": {
        "wallTime": 1775703791217,
        "logical": 5,
        "nodeId": "order-service-01KNR335"
      },
      "wallClock": 1775703791217,
      "type": "random",
      "serviceName": "order-service",
      "operationName": "Math.random()",
      "sequence": 44,
      "data": {
        "value": 0.17859497022691107
      },
      "durationMs": 0,
      "error": null,
      "tags": {}
    },
    {
      "id": "01KNR335KHRJ0YWXMNDH8SBMN6",
      "traceId": "b2ea38771710f1e92e26a3e6ac3a95fc",
      "spanId": "9923c77572c21ea4",
      "parentSpanId": null,
      "hlc": {
        "wallTime": 1775703791217,
        "logical": 6,
        "nodeId": "order-service-01KNR335"
      },
      "wallClock": 1775703791217,
      "type": "random",
      "serviceName": "order-service",
      "operationName": "Math.random()",
      "sequence": 45,
      "data": {
        "value": 0.24815704089637658
      },
      "durationMs": 0,
      "error": null,
      "tags": {}
    },
    {
      "id": "01KNR335KH16JB9N8YYD3E18ZF",
      "traceId": "b2ea38771710f1e92e26a3e6ac3a95fc",
      "spanId": "9923c77572c21ea4",
      "parentSpanId": null,
      "hlc": {
        "wallTime": 1775703791217,
        "logical": 7,
        "nodeId": "order-service-01KNR335"
      },
      "wallClock": 1775703791217,
      "type": "random",
      "serviceName": "order-service",
      "operationName": "Math.random()",
      "sequence": 46,
      "data": {
        "value": 0.8908123347351379
      },
      "durationMs": 0,
      "error": null,
      "tags": {}
    },
    {
      "id": "01KNR335KHN400XDZ01KBAPG8Q",
      "traceId": "b2ea38771710f1e92e26a3e6ac3a95fc",
      "spanId": "9923c77572c21ea4",
      "parentSpanId": null,
      "hlc": {
        "wallTime": 1775703791217,
        "logical": 8,
        "nodeId": "order-service-01KNR335"
      },
      "wallClock": 1775703791217,
      "type": "random",
      "serviceName": "order-service",
      "operationName": "Math.random()",
      "sequence": 47,
      "data": {
        "value": 0.9304446503029226
      },
      "durationMs": 0,
      "error": null,
      "tags": {}
    },
    {
      "id": "01KNR335KHMK5GH2EJSN69SD19",
      "traceId": "b2ea38771710f1e92e26a3e6ac3a95fc",
      "spanId": "9923c77572c21ea4",
      "parentSpanId": null,
      "hlc": {
        "wallTime": 1775703791217,
        "logical": 9,
        "nodeId": "order-service-01KNR335"
      },
      "wallClock": 1775703791217,
      "type": "random",
      "serviceName": "order-service",
      "operationName": "Math.random()",
      "sequence": 48,
      "data": {
        "value": 0.8621943165796466
      },
      "durationMs": 0,
      "error": null,
      "tags": {}
    },
    {
      "id": "01KNR335KHXP03HTZM3JGSNGZW",
      "traceId": "b2ea38771710f1e92e26a3e6ac3a95fc",
      "spanId": "9923c77572c21ea4",
      "parentSpanId": null,
      "hlc": {
        "wallTime": 1775703791217,
        "logical": 10,
        "nodeId": "order-service-01KNR335"
      },
      "wallClock": 1775703791217,
      "type": "random",
      "serviceName": "order-service",
      "operationName": "Math.random()",
      "sequence": 49,
      "data": {
        "value": 0.3162782278413233
      },
      "durationMs": 0,
      "error": null,
      "tags": {}
    },
    {
      "id": "01KNR335KH61RX1CYG5W3YBC6G",
      "traceId": "b2ea38771710f1e92e26a3e6ac3a95fc",
      "spanId": "9923c77572c21ea4",
      "parentSpanId": null,
      "hlc": {
        "wallTime": 1775703791217,
        "logical": 11,
        "nodeId": "order-service-01KNR335"
      },
      "wallClock": 1775703791217,
      "type": "random",
      "serviceName": "order-service",
      "operationName": "Math.random()",
      "sequence": 50,
      "data": {
        "value": 0.33284691562857127
      },
      "durationMs": 0,
      "error": null,
      "tags": {}
    },
    {
      "id": "01KNR335KH9A7XF4MQ8PVBVDE5",
      "traceId": "b2ea38771710f1e92e26a3e6ac3a95fc",
      "spanId": "9923c77572c21ea4",
      "parentSpanId": null,
      "hlc": {
        "wallTime": 1775703791217,
        "logical": 12,
        "nodeId": "order-service-01KNR335"
      },
      "wallClock": 1775703791217,
      "type": "random",
      "serviceName": "order-service",
      "operationName": "Math.random()",
      "sequence": 51,
      "data": {
        "value": 0.06492968076548267
      },
      "durationMs": 0,
      "error": null,
      "tags": {}
    },
    {
      "id": "01KNR335KHP8F8ARSW0NPNSM3C",
      "traceId": "b2ea38771710f1e92e26a3e6ac3a95fc",
      "spanId": "9923c77572c21ea4",
      "parentSpanId": null,
      "hlc": {
        "wallTime": 1775703791217,
        "logical": 13,
        "nodeId": "order-service-01KNR335"
      },
      "wallClock": 1775703791217,
      "type": "random",
      "serviceName": "order-service",
      "operationName": "Math.random()",
      "sequence": 52,
      "data": {
        "value": 0.5880844337164866
      },
      "durationMs": 0,
      "error": null,
      "tags": {}
    },
    {
      "id": "01KNR335KHBH5CBFH77TH7DQVX",
      "traceId": "b2ea38771710f1e92e26a3e6ac3a95fc",
      "spanId": "9923c77572c21ea4",
      "parentSpanId": null,
      "hlc": {
        "wallTime": 1775703791217,
        "logical": 14,
        "nodeId": "order-service-01KNR335"
      },
      "wallClock": 1775703791217,
      "type": "random",
      "serviceName": "order-service",
      "operationName": "Math.random()",
      "sequence": 53,
      "data": {
        "value": 0.45504248763069055
      },
      "durationMs": 0,
      "error": null,
      "tags": {}
    },
    {
      "id": "01KNR335KHJAVZVAHR5AZ7G9Q2",
      "traceId": "b2ea38771710f1e92e26a3e6ac3a95fc",
      "spanId": "9923c77572c21ea4",
      "parentSpanId": null,
      "hlc": {
        "wallTime": 1775703791217,
        "logical": 15,
        "nodeId": "order-service-01KNR335"
      },
      "wallClock": 1775703791217,
      "type": "random",
      "serviceName": "order-service",
      "operationName": "Math.random()",
      "sequence": 54,
      "data": {
        "value": 0.6879506725698817
      },
      "durationMs": 0,
      "error": null,
      "tags": {}
    },
    {
      "id": "01KNR335KHG6TWB966MYPQANST",
      "traceId": "b2ea38771710f1e92e26a3e6ac3a95fc",
      "spanId": "9923c77572c21ea4",
      "parentSpanId": null,
      "hlc": {
        "wallTime": 1775703791217,
        "logical": 16,
        "nodeId": "order-service-01KNR335"
      },
      "wallClock": 1775703791217,
      "type": "random",
      "serviceName": "order-service",
      "operationName": "Math.random()",
      "sequence": 55,
      "data": {
        "value": 0.7521577390413019
      },
      "durationMs": 0,
      "error": null,
      "tags": {}
    },
    {
      "id": "01KNR335KHWA3EFNRGPCSMM0N7",
      "traceId": "b2ea38771710f1e92e26a3e6ac3a95fc",
      "spanId": "9923c77572c21ea4",
      "parentSpanId": null,
      "hlc": {
        "wallTime": 1775703791217,
        "logical": 17,
        "nodeId": "order-service-01KNR335"
      },
      "wallClock": 1775703791217,
      "type": "random",
      "serviceName": "order-service",
      "operationName": "Math.random()",
      "sequence": 56,
      "data": {
        "value": 0.16868987265776025
      },
      "durationMs": 0,
      "error": null,
      "tags": {}
    },
    {
      "id": "01KNR335KHH4D57WXVAA2JEPR5",
      "traceId": "b2ea38771710f1e92e26a3e6ac3a95fc",
      "spanId": "9923c77572c21ea4",
      "parentSpanId": null,
      "hlc": {
        "wallTime": 1775703791217,
        "logical": 0,
        "nodeId": "order-service-01KNR335"
      },
      "wallClock": 1775703791217,
      "type": "http_response_out",
      "serviceName": "order-service",
      "operationName": "200 POST /api/orders",
      "sequence": 57,
      "data": {
        "statusCode": 200,
        "headers": {
          "x-powered-by": "Express",
          "traceparent": "00-b2ea38771710f1e92e26a3e6ac3a95fc-9923c77572c21ea4-01",
          "content-type": "application/json; charset=utf-8",
          "content-length": "180",
          "etag": "W/\"b4-KeYml8lXYHVTUynHerNeylysXI0\""
        },
        "body": {
          "orderId": "ORD-PYQ2MQ",
          "userId": "4",
          "userName": "Fatma Celik",
          "orderTotal": 300,
          "status": "rejected",
          "reason": "Insufficient credit",
          "timestamp": 1775703791209,
          "confirmationCode": null
        }
      },
      "durationMs": 8,
      "error": null,
      "tags": {}
    }
  ],
  "metadata": {
    "nodeVersion": "v25.2.1",
    "platform": "darwin",
    "probeVersion": "0.1.0",
    "hasError": false,
    "totalDurationMs": 8
  }
}